verilog/rtl/mac_unit.v
module mac (
    input clk,
    input rst,
    input spike_in,                 // 1-bit input
    input signed [7:0] weight,      // 8-bit signed weight
    input signed [15:0] acc_in,     // current membrane potential
    output reg signed [15:0] acc_out // updated potential
);

always @(posedge clk or posedge rst) begin
    if (rst)
        acc_out <= 0;
    else if (spike_in)
        acc_out <= acc_in + weight;
    else
        acc_out <= acc_in;
end

endmodule

verilog/tb/tb_mac.v
`timescale 1ns/1ps

module tb_mac;
  // Inputs
  reg clk;
  reg rst;
  reg spike_in;
  reg signed [7:0] weight;
  reg signed [15:0] acc_in;

  // Output
  wire signed [15:0] acc_out;

  // Instantiate the MAC module
  mac uut (
    .clk(clk),
    .rst(rst),
    .spike_in(spike_in),
    .weight(weight),
    .acc_in(acc_in),
    .acc_out(acc_out)
  );

  // Clock generation
  always #5 clk = ~clk;  // 10ns period

  initial begin
    // Initialize signals
    $dumpfile("wave.vcd");   // for GTKWave
    $dumpvars(0, tb_mac);    // dump everything

    clk = 0;
    rst = 1;
    spike_in = 0;
    weight = 0;
    acc_in = 0;

    #10 rst = 0;

    // Test case 1: No spike, acc should hold
    acc_in = 16'sd10;
    weight = 8'sd3;
    spike_in = 0;
    #10;

    // Test case 2: Spike with positive weight
    spike_in = 1;
    #10;

    // Test case 3: Spike with negative weight
    acc_in = acc_out;    // continue accumulating
    weight = -8'sd2;
    #10;

    // Test case 4: No spike
    spike_in = 0;
    #10;

    // Done
    $finish;
  end

endmodule

simulation/waveform_mac.vcd
$date
	Mon Jul 21 15:04:16 2025
$end
$version
	Icarus Verilog
$end
$timescale
	1ps
$end
$scope module tb_mac $end
$var wire 16 ! acc_out [15:0] $end
$var reg 16 " acc_in [15:0] $end
$var reg 1 # clk $end
$var reg 1 $ rst $end
$var reg 1 % spike_in $end
$var reg 8 & weight [7:0] $end
$scope module uut $end
$var wire 16 ' acc_in [15:0] $end
$var wire 1 # clk $end
$var wire 1 $ rst $end
$var wire 1 % spike_in $end
$var wire 8 ( weight [7:0] $end
$var reg 16 ) acc_out [15:0] $end
$upscope $end
$upscope $end
$enddefinitions $end
$comment Show the parameter values. $end
$dumpall
$end
#0
$dumpvars
b0 )
b0 (
b0 '
b0 &
0%
1$
0#
b0 "
b0 !
$end
#5000
1#
#10000
0#
b11 &
b11 (
b1010 "
b1010 '
0$
#15000
b1010 !
b1010 )
1#
#20000
0#
1%
#25000
b1101 !
b1101 )
1#
#30000
0#
b11111110 &
b11111110 (
b1101 "
b1101 '
#35000
b1011 !
b1011 )
1#
#40000
0#
0%
#45000
b1101 !
b1101 )
1#
